reactant/__init__.py
reactant/exceptions.py
reactant/main.py
reactant/orm/__init__.py
reactant/orm/django.py
reactant/orm/peewee.py
reactant/orm/sqla.py
reactant/renderer/__init__.py
reactant/renderer/django.py
reactant/renderer/peewee.py
reactant/renderer/sqla.py
reactant/run.py
reactant/templates/django_models.txt.jinja
reactant/templates/django_serializers.txt.jinja
reactant/templates/django_urls_class.txt.jinja
reactant/templates/django_urls_func.txt.jinja
reactant/templates/django_urls_router.txt.jinja
reactant/templates/django_views_class.txt.jinja
reactant/templates/django_views_func.txt.jinja
reactant/templates/django_views_model_view_set.txt.jinja
reactant/templates/peewee_models.txt.jinja
reactant/templates/sqla_models_classical.txt.jinja
reactant/templates/sqla_models_declarative.txt.jinja
reactant/utils.py
reactant-0.6.0.dist-info/entry_points.txt
reactant-0.6.0.dist-info/LICENSE
reactant-0.6.0.dist-info/WHEEL
reactant-0.6.0.dist-info/METADATA
reactant-0.6.0.dist-info/RECORD
