Metadata-Version: 2.1
Name: reactant
Version: 0.6.0
Summary: Generate code for models, views, and urls based on Python type annotations.
License: MIT
Author: Neil Van
Author-email: nvq.alino@gmail.com
Requires-Python: >=3.8,<4.0
Classifier: License :: OSI Approved :: MIT License
Classifier: Programming Language :: Python :: 3
Classifier: Programming Language :: Python :: 3.10
Classifier: Programming Language :: Python :: 3.8
Classifier: Programming Language :: Python :: 3.9
Requires-Dist: Jinja2 (>=3.0.1,<4.0.0)
Requires-Dist: black (>=21.8b0,<22.0)
Requires-Dist: click (>=8.0.1,<9.0.0)
Requires-Dist: pydantic (>=1.8.2,<2.0.0)
